libnftinema/__init__.py
libnftinema/client.py
libnftinema/common.py
libnftinema/runtests.py
libnftinema/server.py
libnftinema/structs.py
libnftinema/test_client.py
libnftinema/test_common.py
libnftinema/test_server.py
libnftinema/test_settings.py
libnftinema/testapp/__init__.py
libnftinema/testapp/apps.py
libnftinema/testapp/handlers.py
libnftinema/testapp/models.py
libnftinema/testapp/urls.py
libnftinema/testapp/views.py
libnftinema/testapp/migrations/0001_initial.py
libnftinema/testapp/migrations/__init__.py
libnftinema-24.9.5.dist-info/METADATA
libnftinema-24.9.5.dist-info/WHEEL
libnftinema-24.9.5.dist-info/RECORD
