Metadata-Version: 2.3
Name: libnftinema
Version: 24.9.5
Summary: Secure client/server requests with JWT
Author-email: yokotoka <hey@yokotoka.is>
Requires-Python: >=3.10
Requires-Dist: arrow>=1.3.0
Requires-Dist: djangorestframework>=3.15.2
Requires-Dist: loguru>=0.7.2
Requires-Dist: pyjwt>=2.9.0
Requires-Dist: pytest-django>=4.7.0
Requires-Dist: requests>=2.32.3
